ossval/__init__.py
ossval/cache.py
ossval/cli.py
ossval/core.py
ossval/models.py
ossval/analyzers/__init__.py
ossval/analyzers/complexity.py
ossval/analyzers/git_history.py
ossval/analyzers/halstead.py
ossval/analyzers/health.py
ossval/analyzers/maintainability.py
ossval/analyzers/repo_finder.py
ossval/analyzers/sloc.py
ossval/data/__init__.py
ossval/data/multipliers.py
ossval/data/project_types.py
ossval/data/salaries.py
ossval/estimators/__init__.py
ossval/estimators/base.py
ossval/estimators/cocomo.py
ossval/estimators/sloccount.py
ossval/output/__init__.py
ossval/output/csv.py
ossval/output/json.py
ossval/output/text.py
ossval/parsers/__init__.py
ossval/parsers/base.py
ossval/parsers/cargo.py
ossval/parsers/cyclonedx.py
ossval/parsers/go_mod.py
ossval/parsers/go_sum.py
ossval/parsers/gradle.py
ossval/parsers/maven.py
ossval/parsers/package_json.py
ossval/parsers/package_lock.py
ossval/parsers/pipfile.py
ossval/parsers/poetry.py
ossval/parsers/pyproject.py
ossval/parsers/requirements.py
ossval/parsers/simple.py
ossval/parsers/spdx.py
ossval/parsers/yarn.py
ossval-1.2.2.dist-info/licenses/LICENSE
ossval-1.2.2.dist-info/METADATA
ossval-1.2.2.dist-info/WHEEL
ossval-1.2.2.dist-info/entry_points.txt
ossval-1.2.2.dist-info/top_level.txt
ossval-1.2.2.dist-info/RECORD
