Metadata-Version: 2.4
Name: ossval
Version: 1.2.2
Summary: Open Source Software Valuation - Calculate development cost savings from OSS dependencies
Author-email: "Oscar Valenzuela B." <oscar.valenzuela.b@gmail.com>
License: Apache-2.0
Project-URL: Homepage, https://github.com/SemClone/ossval
Project-URL: Repository, https://github.com/SemClone/ossval
Project-URL: Documentation, https://github.com/SemClone/ossval#readme
Project-URL: Bug Tracker, https://github.com/SemClone/ossval/issues
Project-URL: Source Code, https://github.com/SemClone/ossval
Keywords: oss,sbom,valuation,cost,cocomo,dependencies
Classifier: Development Status :: 3 - Alpha
Classifier: Intended Audience :: Developers
Classifier: License :: OSI Approved :: Apache Software License
Classifier: Programming Language :: Python :: 3
Classifier: Programming Language :: Python :: 3.10
Classifier: Programming Language :: Python :: 3.11
Classifier: Programming Language :: Python :: 3.12
Classifier: Programming Language :: Python :: 3.13
Classifier: Topic :: Software Development :: Libraries
Classifier: Topic :: Software Development :: Quality Assurance
Requires-Python: >=3.10
License-File: LICENSE
Requires-Dist: click>=8.1.0
Requires-Dist: pydantic>=2.0.0
Requires-Dist: httpx>=0.25.0
Requires-Dist: rich>=13.0.0
Requires-Dist: gitpython>=3.1.0
Requires-Dist: pygount>=1.6.0
Requires-Dist: radon>=6.0.0
Requires-Dist: diskcache>=5.6.0
Requires-Dist: tomli>=2.0.0; python_version < "3.11"
Requires-Dist: aiofiles>=23.0.0
Provides-Extra: multilang
Requires-Dist: tree-sitter<0.22.0,>=0.21.0; python_version < "3.13" and extra == "multilang"
Requires-Dist: tree-sitter-languages>=1.10.0; python_version < "3.13" and extra == "multilang"
Provides-Extra: dev
Requires-Dist: pytest>=7.0.0; extra == "dev"
Requires-Dist: pytest-asyncio>=0.21.0; extra == "dev"
Requires-Dist: pytest-cov>=4.0.0; extra == "dev"
Requires-Dist: ruff>=0.1.0; extra == "dev"
Requires-Dist: mypy>=1.0.0; extra == "dev"
Requires-Dist: types-toml; extra == "dev"
Requires-Dist: types-aiofiles; extra == "dev"
Dynamic: license-file
